pdg/__init__.py
pdg/api.py
pdg/data.py
pdg/decay.py
pdg/errors.py
pdg/measurement.py
pdg/particle.py
pdg/pdg.sqlite
pdg/units.py
pdg/utils.py
pdg-0.2.1.dist-info/licenses/LICENSE.txt
pdg-0.2.1.dist-info/METADATA
pdg-0.2.1.dist-info/WHEEL
pdg-0.2.1.dist-info/top_level.txt
pdg-0.2.1.dist-info/RECORD
