Metadata-Version: 2.4
Name: pdg
Version: 0.2.1
Summary: Python API for accessing PDG data
Home-page: https://pdg.lbl.gov
Author: Particle Data Group
Author-email: jberinger@lbl.gov
License: Modified BSD
Project-URL: Documentation, https://pdgapi.lbl.gov/doc/
Project-URL: GitHub, https://github.com/particledatagroup/api
Project-URL: Changelog, https://github.com/particledatagroup/api/blob/main/CHANGELOG.md
Keywords: PDG,particle physics
Classifier: Development Status :: 5 - Production/Stable
Classifier: Environment :: Console
Classifier: Intended Audience :: Science/Research
Classifier: Intended Audience :: Developers
Classifier: Programming Language :: Python :: 2.7
Classifier: Programming Language :: Python :: 3
Classifier: Topic :: Database :: Front-Ends
Classifier: Topic :: Scientific/Engineering
Classifier: Topic :: Scientific/Engineering :: Physics
License-File: LICENSE.txt
Requires-Dist: SQLAlchemy>=1.4
Dynamic: author
Dynamic: author-email
Dynamic: classifier
Dynamic: description
Dynamic: description-content-type
Dynamic: home-page
Dynamic: keywords
Dynamic: license
Dynamic: license-file
Dynamic: project-url
Dynamic: requires-dist
Dynamic: summary
